{
  "mapSlug": "overpass",
  "mapName": "Overpass",
  "strategies": [
    {
      "side": "T",
      "name": "T slot 1",
      "description": "Overpass T preset for numpad 1: rush B monster smoke bridge flash over.",
      "creator": "System",
      "message": "rush B monster smoke bridge flash over",
      "meta": {}
    },
    {
      "side": "T",
      "name": "T slot 2",
      "description": "Overpass T preset for numpad 2: monster + short split smoke heaven.",
      "creator": "System",
      "message": "monster + short split smoke heaven",
      "meta": {}
    },
    {
      "side": "T",
      "name": "T slot 3",
      "description": "Overpass T preset for numpad 3: mid control connector smoke.",
      "creator": "System",
      "message": "mid control connector smoke",
      "meta": {}
    },
    {
      "side": "T",
      "name": "T slot 4",
      "description": "Overpass T preset for numpad 4: long + short go A smoke truck.",
      "creator": "System",
      "message": "long + short go A smoke truck",
      "meta": {}
    },
    {
      "side": "T",
      "name": "T slot 5",
      "description": "Overpass T preset for numpad 5: [fake] long smoke A go B monster.",
      "creator": "System",
      "message": "[fake] long smoke A go B monster",
      "meta": {}
    },
    {
      "side": "T",
      "name": "T slot 6",
      "description": "Overpass T preset for numpad 6: B site smoke heaven + bridge.",
      "creator": "System",
      "message": "B site smoke heaven + bridge",
      "meta": {}
    },
    {
      "side": "T",
      "name": "T slot 7",
      "description": "Overpass T preset for numpad 7: A long contact flash.",
      "creator": "System",
      "message": "A long contact flash",
      "meta": {}
    },
    {
      "side": "T",
      "name": "T slot 8",
      "description": "Overpass T preset for numpad 8: fast B explode flash monster.",
      "creator": "System",
      "message": "fast B explode flash monster",
      "meta": {}
    },
    {
      "side": "T",
      "name": "T slot 9",
      "description": "Overpass T preset for numpad 9: hide connector till 1:00 then go A smoke truck + bank.",
      "creator": "System",
      "message": "hide connector till 1:00 then go A smoke truck + bank",
      "meta": {}
    },
    {
      "side": "CT",
      "name": "CT slot 1",
      "description": "Overpass CT preset for numpad 1: fountain control.",
      "creator": "System",
      "message": "fountain control",
      "meta": {}
    },
    {
      "side": "CT",
      "name": "CT slot 2",
      "description": "Overpass CT preset for numpad 2: 3 B hold.",
      "creator": "System",
      "message": "3 B hold",
      "meta": {}
    },
    {
      "side": "CT",
      "name": "CT slot 3",
      "description": "Overpass CT preset for numpad 3: push monster.",
      "creator": "System",
      "message": "push monster",
      "meta": {}
    },
    {
      "side": "CT",
      "name": "CT slot 4",
      "description": "Overpass CT preset for numpad 4: A crossfire.",
      "creator": "System",
      "message": "A crossfire",
      "meta": {}
    },
    {
      "side": "CT",
      "name": "CT slot 5",
      "description": "Overpass CT preset for numpad 5: stack B.",
      "creator": "System",
      "message": "stack B",
      "meta": {}
    },
    {
      "side": "CT",
      "name": "CT slot 6",
      "description": "Overpass CT preset for numpad 6: retake A.",
      "creator": "System",
      "message": "retake A",
      "meta": {}
    },
    {
      "side": "CT",
      "name": "CT slot 7",
      "description": "Overpass CT preset for numpad 7: connector control.",
      "creator": "System",
      "message": "connector control",
      "meta": {}
    },
    {
      "side": "CT",
      "name": "CT slot 8",
      "description": "Overpass CT preset for numpad 8: long push.",
      "creator": "System",
      "message": "long push",
      "meta": {}
    },
    {
      "side": "CT",
      "name": "CT slot 9",
      "description": "Overpass CT preset for numpad 9: save setup.",
      "creator": "System",
      "message": "save setup",
      "meta": {}
    }
  ]
}
